pypipeline/__init__.py
pypipeline_esb-1.0.0.dist-info/DESCRIPTION.rst
pypipeline_esb-1.0.0.dist-info/METADATA
pypipeline_esb-1.0.0.dist-info/RECORD
pypipeline_esb-1.0.0.dist-info/WHEEL
pypipeline_esb-1.0.0.dist-info/metadata.json
pypipeline_esb-1.0.0.dist-info/top_level.txt
